loinchpo/__init__.py
loinchpo/main.py
loinchpo/core/Cleaner.py
loinchpo/core/ConceptSynonymTransformer.py
loinchpo/core/MeasurementTransformer.py
loinchpo/core/OMOPTransformer.py
loinchpo/core/QueryResolver.py
loinchpo/core/__init__.py
loinchpo/error/ClinicalParsingError.py
loinchpo/error/LoincHpoDataValidationError.py
loinchpo/error/LoincHpoFileValidationError.py
loinchpo/error/LoincHpoParsingError.py
loinchpo/error/__init__.py
loinchpo/io/AnnotationParser.py
loinchpo/io/ClinicalTableParser.py
loinchpo/io/QueryFileParser.py
loinchpo/io/Utility.py
loinchpo/io/__init__.py
loinchpo/model/ClinicalTableColumns.py
loinchpo/model/ClinicalTableName.py
loinchpo/model/LoincId.py
loinchpo/model/LoincScale.py
loinchpo/model/Query.py
loinchpo/model/__init__.py
loinchpo/tests/__init__.py
loinchpo/tests/coverage.svg
loinchpo/tests/test_annotation_file.tsv
loinchpo/tests/test_cli.py
loinchpo/tests/test_query.tsv
loinchpo/tests/__pycache__/__init__.cpython-310.pyc
loinchpo/tests/__pycache__/__init__.cpython-311.pyc
loinchpo/tests/__pycache__/__init__.cpython-39.pyc
loinchpo/tests/__pycache__/test_cli.cpython-310.pyc
loinchpo/tests/__pycache__/test_cli.cpython-311.pyc
loinchpo/tests/__pycache__/test_cli.cpython-39.pyc
loinchpo/tests/core/__init__.py
loinchpo/tests/core/measurement.csv
loinchpo/tests/core/test_concept_synonym_transformer.py
loinchpo/tests/core/test_measurement_transformer.py
loinchpo/tests/core/test_omop_transform.py
loinchpo/tests/core/test_query_resolver.py
loinchpo/tests/core/transformer_data.py
loinchpo/tests/core/__pycache__/__init__.cpython-310.pyc
loinchpo/tests/core/__pycache__/__init__.cpython-311.pyc
loinchpo/tests/core/__pycache__/__init__.cpython-39.pyc
loinchpo/tests/core/__pycache__/test_concept_synonym_transformer.cpython-310.pyc
loinchpo/tests/core/__pycache__/test_concept_synonym_transformer.cpython-311.pyc
loinchpo/tests/core/__pycache__/test_concept_synonym_transformer.cpython-39.pyc
loinchpo-1.2.0.dist-info/LICENSE.txt
loinchpo-1.2.0.dist-info/METADATA
loinchpo-1.2.0.dist-info/WHEEL
loinchpo-1.2.0.dist-info/entry_points.txt
loinchpo-1.2.0.dist-info/top_level.txt
loinchpo-1.2.0.dist-info/RECORD
