Metadata-Version: 2.1
Name: loinchpo
Version: 1.2.0
Summary: A library to transform loinc measurements into hpo terms.
Author-email: Michael Gargano <michael.gargano@protonmail.com>
License: GNU GENERAL PUBLIC LICENSE
Project-URL: documentation, https://thejacksonlaboratory.github.io/loinchpo
Project-URL: repository, https://github.com/TheJacksonLaboratory/loinchpo
Keywords: loinc,hpo,clinical,omop
Classifier: Programming Language :: Python :: 3
Classifier: Operating System :: OS Independent
Requires-Python: >=3.8
License-File: LICENSE.txt
Requires-Dist: click
Requires-Dist: ddt
Requires-Dist: pandas
Requires-Dist: pyspark
Provides-Extra: dev
Requires-Dist: sphinx ; extra == 'dev'
Requires-Dist: sphinx-rtd-theme ; extra == 'dev'
Requires-Dist: coverage-badge ; extra == 'dev'
Requires-Dist: twine ; extra == 'dev'
